{
  "required": true,
  "package": "net.ds.mixin",
  "compatibilityLevel": "JAVA_21",
  "mixins": [
    "item.EnderPearlMixin",
    "block.EndPortalBlockMixin",
    "EntityMixin",
    "item.EyeOfEnderMixin",
    "item.FireworkRocketItemMixin",
    "LivingEntityMixin",
    "block.NetherPortalBlockMixin",
    "server.ServerPlayerEntityMixin",
    "item.TridentItemMixin"
  ],
  "client": [
    "client.LeaveButtonMixin",
    "client.ClientCommonNetworkHandlerMixin",
    "client.ZipResourcePackMixin"
  ],
  "server": [
    "server.ResourcePackMixin"
  ],
  "injectors": {
    "defaultRequire": 1
  },
  "overwrites": {
    "requireAnnotations": true
  }

}